singlepointsim/__init__.py
singlepointsim/__main__.py
singlepointsim/compile_umat.py
singlepointsim/driver.py
singlepointsim/parse_sps_input.py
singlepointsim/sps_input.py
singlepointsim/sps_outputs.py
singlepointsim/sps_step.py
singlepointsim/loading_scenarios/__init__.py
singlepointsim/loading_scenarios/base.py
singlepointsim/loading_scenarios/biaxial_tension.py
singlepointsim/loading_scenarios/compression_torsion.py
singlepointsim/loading_scenarios/plane_strain.py
singlepointsim/loading_scenarios/tension_compression.py
singlepointsim/loading_scenarios/torsion.py
singlepointsim-0.0.6.dist-info/LICENSE
singlepointsim-0.0.6.dist-info/METADATA
singlepointsim-0.0.6.dist-info/WHEEL
singlepointsim-0.0.6.dist-info/top_level.txt
singlepointsim-0.0.6.dist-info/RECORD
