Metadata-Version: 2.1
Name: singlepointsim
Version: 0.0.6
Summary: Abaqus FEA UMAT interoperability layer for quick, pythonic single-point analysis and material-model validation.
Author-email: Clark Hensley <clarkhensley@duck.com>
Maintainer-email: Clark Hensley <clarkhensley@duck.com>
License: MIT License
License-File: LICENSE
Requires-Dist: numpy
Requires-Dist: pandas
Requires-Dist: meson>=1.5.1
Requires-Dist: thick
Requires-Dist: tomli; python_version < "3.11"
Provides-Extra: dev
Requires-Dist: mypy; extra == "dev"
Requires-Dist: ruff; extra == "dev"
